FaceExtractor-0.1.5.dist-info/DESCRIPTION.rst
FaceExtractor-0.1.5.dist-info/METADATA
FaceExtractor-0.1.5.dist-info/RECORD
FaceExtractor-0.1.5.dist-info/WHEEL
FaceExtractor-0.1.5.dist-info/metadata.json
FaceExtractor-0.1.5.dist-info/top_level.txt
face_extractor/__init__.py
face_extractor/extractor.py
face_extractor/data/haarcascade_frontalface_alt.xml
face_extractor/data/haarcascade_frontalface_alt2.xml
face_extractor/data/haarcascade_frontalface_alt_tree.xml
face_extractor/data/haarcascade_frontalface_default.xml
